pybop/__init__.py
pybop/_classification.py
pybop/_dataset.py
pybop/_evaluation.py
pybop/_experiment.py
pybop/_utils.py
pybop/_version.py
pybop/applications/__init__.py
pybop/applications/base_method.py
pybop/applications/gitt_methods.py
pybop/applications/ocp_methods.py
pybop/costs/__init__.py
pybop/costs/_likelihoods.py
pybop/costs/_weighted_cost.py
pybop/costs/base_cost.py
pybop/costs/design_costs.py
pybop/costs/error_measures.py
pybop/costs/fitting_costs.py
pybop/experimental/jax_costs.py
pybop/models/__init__.py
pybop/models/_exponential_decay.py
pybop/models/base_model.py
pybop/models/empirical/__init__.py
pybop/models/empirical/base_ecm.py
pybop/models/empirical/ecm.py
pybop/models/lithium_ion/__init__.py
pybop/models/lithium_ion/base_echem.py
pybop/models/lithium_ion/basic_SPM.py
pybop/models/lithium_ion/basic_SPMe.py
pybop/models/lithium_ion/basic_SP_diffusion.py
pybop/models/lithium_ion/echem.py
pybop/models/lithium_ion/weppner_huggins.py
pybop/observers/__init__.py
pybop/observers/observer.py
pybop/observers/unscented_kalman.py
pybop/optimisers/__init__.py
pybop/optimisers/_adamw.py
pybop/optimisers/_cost_interface.py
pybop/optimisers/_cuckoo.py
pybop/optimisers/_gradient_descent.py
pybop/optimisers/_irprop_plus.py
pybop/optimisers/_random_search.py
pybop/optimisers/_result.py
pybop/optimisers/_simulated_annealing.py
pybop/optimisers/base_optimiser.py
pybop/optimisers/base_pints_optimiser.py
pybop/optimisers/optimisation.py
pybop/optimisers/pints_optimisers.py
pybop/optimisers/scipy_optimisers.py
pybop/parameters/__init__.py
pybop/parameters/parameter.py
pybop/parameters/parameter_set.py
pybop/parameters/priors.py
pybop/plot/__init__.py
pybop/plot/contour.py
pybop/plot/convergence.py
pybop/plot/dataset.py
pybop/plot/nyquist.py
pybop/plot/parameters.py
pybop/plot/plotly_manager.py
pybop/plot/problem.py
pybop/plot/standard_plots.py
pybop/plot/voronoi.py
pybop/problems/__init__.py
pybop/problems/base_problem.py
pybop/problems/design_problem.py
pybop-25.6.dist-info/licenses/LICENSE
pybop-25.6.dist-info/METADATA
pybop-25.6.dist-info/WHEEL
pybop-25.6.dist-info/top_level.txt
pybop-25.6.dist-info/RECORD
