Metadata-Version: 2.4
Name: pybop
Version: 25.6
Summary: Python Battery Optimisation and Parameterisation
Author: The PyBOP Team
Maintainer: The PyBOP Team
License: BSD 3-Clause License
Project-URL: Homepage, https://github.com/pybop-team/PyBOP
Project-URL: Documentation, https://pybop-docs.readthedocs.io
Project-URL: Repository, https://github.com/pybop-team/PyBOP
Project-URL: Releases, https://github.com/pybop-team/PyBOP/releases
Project-URL: Changelog, https://github.com/pybop-team/PyBOP/blob/develop/CHANGELOG.md
Classifier: Development Status :: 3 - Alpha
Classifier: License :: OSI Approved :: BSD License
Classifier: Programming Language :: Python :: 3.9
Classifier: Programming Language :: Python :: 3.10
Classifier: Programming Language :: Python :: 3.11
Classifier: Programming Language :: Python :: 3.12
Classifier: Intended Audience :: Science/Research
Classifier: Topic :: Scientific/Engineering
Requires-Python: <3.13,>=3.9
License-File: LICENSE
Requires-Dist: pybamm[jax]>=24.5.1
Requires-Dist: numpy<2.0,>=1.16
Requires-Dist: scipy>=1.3
Requires-Dist: pints>=0.5
Requires-Dist: SALib>=1.5
Provides-Extra: plot
Requires-Dist: plotly>=5.0; extra == "plot"
Provides-Extra: docs
Requires-Dist: pydata-sphinx-theme; extra == "docs"
Requires-Dist: sphinx>=6; extra == "docs"
Requires-Dist: sphinx-autobuild; extra == "docs"
Requires-Dist: sphinx-autoapi; extra == "docs"
Requires-Dist: sphinx_copybutton; extra == "docs"
Requires-Dist: sphinx_favicon; extra == "docs"
Requires-Dist: sphinx_design; extra == "docs"
Requires-Dist: myst-parser; extra == "docs"
Provides-Extra: dev
Requires-Dist: nox[uv]; extra == "dev"
Requires-Dist: nbmake; extra == "dev"
Requires-Dist: pre-commit; extra == "dev"
Requires-Dist: pytest>=6; extra == "dev"
Requires-Dist: pytest-cov; extra == "dev"
Requires-Dist: pytest-mock; extra == "dev"
Requires-Dist: pytest-xdist; extra == "dev"
Requires-Dist: ruff; extra == "dev"
Provides-Extra: scifem
Requires-Dist: scikit-fem>=8.1.0; extra == "scifem"
Provides-Extra: bpx
Requires-Dist: bpx<0.6,>=0.5; extra == "bpx"
Provides-Extra: all
Requires-Dist: pybop[bpx,plot,scifem]; extra == "all"
Dynamic: license-file
